[{"tipo": "entrada", "producto": "Coche beb\u00e9", "cantidad": 17, "fecha": "2026-04-15 23:47:21"}, {"tipo": "salida", "producto": "Coche beb\u00e9", "cantidad": 5, "fecha": "2026-04-15 23:47:43"}, {"tipo": "entrada", "producto": "Coche beb\u00e9", "sku": "COCHE001", "cantidad": 5, "fecha": "2026-04-16 00:09:23"}, {"tipo": "entrada", "producto": "Coche de beb\u00e9 Reversible Pro", "sku": "RPRO001", "cantidad": 100, "fecha": "2026-04-16 00:17:22"}, {"tipo": "salida", "producto": "Coche de beb\u00e9 Reversible Pro", "sku": "RPRO001", "cantidad": 50, "fecha": "2026-04-16 00:17:37"}, {"tipo": "entrada", "producto": "Coche beb\u00e9", "sku": "COCHE001", "cantidad": 500, "fecha": "2026-04-16 00:33:16"}]